aegis_cli/__init__.py
aegis_cli/cli.py
aegis_cli/detectors/__init__.py
aegis_cli/detectors/base_detector.py
aegis_cli/detectors/javascript_detector.py
aegis_cli/detectors/python_detector.py
aegis_cli/generators/__init__.py
aegis_cli/generators/dependabot_yml.py
aegis_cli/generators/helpers.py
aegis_cli/generators/secure_coding_guide.py
aegis_cli/generators/security_md.py
aegis_cli/templates/SECURITY.md.j2
aegis_cli/templates/SecureCodingGuide.md.j2
aegis_cli/templates/dependabot.yml.j2
aegis_cli/utils/__init__.py
praximous_aegis_cli-0.1.0.dist-info/licenses/LICENSE
praximous_aegis_cli-0.1.0.dist-info/METADATA
praximous_aegis_cli-0.1.0.dist-info/WHEEL
praximous_aegis_cli-0.1.0.dist-info/entry_points.txt
praximous_aegis_cli-0.1.0.dist-info/top_level.txt
praximous_aegis_cli-0.1.0.dist-info/RECORD
