Metadata-Version: 2.4
Name: praximous-aegis-cli
Version: 0.1.0
Summary: Automate security documentation for your projects
Author: JamesTheGiblet
License: # MIT License
Project-URL: Homepage, https://github.com/JamesTheGiblet/Project-Aegis-CLI
Project-URL: Repository, https://github.com/JamesTheGiblet/Project-Aegis-CLI
Project-URL: Issues, https://github.com/JamesTheGiblet/Project-Aegis-CLI/issues
Keywords: security,documentation,automation,cli,devsecops
Classifier: Programming Language :: Python :: 3
Classifier: Programming Language :: Python :: 3.8
Classifier: Programming Language :: Python :: 3.9
Classifier: Programming Language :: Python :: 3.10
Classifier: Programming Language :: Python :: 3.11
Requires-Python: >=3.8
License-File: LICENSE
Requires-Dist: click>=8.0.0
Requires-Dist: Jinja2>=3.0.0
Provides-Extra: test
Requires-Dist: pytest>=7.0.0; extra == "test"
Dynamic: license-file
